[
  {
    "p1_id": 12653,
    "p2_id": 76009,
    "p1_name": "Marco Trungelliti",
    "p2_name": "Abedallah Shelbayh",
    "surface": "clay",
    "tournament": "Bad Rappenau Challenger",
    "tournamentId": 21735,
    "match_date": "2026-06-02",
    "p1_win": 0.965,
    "p2_win": 0.035,
    "fair_p1": 1.04,
    "fair_p2": 28.57,
    "elo_diff": 491,
    "elo1": 1885,
    "elo2": 1394,
    "h2h_record": "0-0",
    "h2h_surf": "0-0 on clay",
    "p1_streak": 0,
    "p2_streak": 0,
    "p1_fatigue": 2,
    "p2_fatigue": 1,
    "p1_fatigue.1": 2,
    "p2_fatigue.1": 1,
    "p1_serve_in": 62.6,
    "p2_serve_in": 62.2,
    "p1_serve_won": 72.4,
    "p2_serve_won": 72,
    "p1_second_won": 55.6,
    "p2_second_won": 51.8,
    "p1_bp_conv": 45.9,
    "p2_bp_conv": 49.8,
    "p1_win_rate": 70.2,
    "p2_win_rate": 38.6,
    "tour": "atp",
    "generated": "2026-06-02 07:06",
    "p1_flag": "ar",
    "p2_flag": "",
    "market_flag": false
  },
  {
    "p1_id": 85851,
    "p2_id": 51846,
    "p1_name": "Luka Mikrut",
    "p2_name": "Alex Marti Pujolras",
    "surface": "clay",
    "tournament": "Bad Rappenau Challenger",
    "tournamentId": 21735,
    "match_date": "2026-06-02",
    "p1_win": 0.893,
    "p2_win": 0.107,
    "fair_p1": 1.12,
    "fair_p2": 9.35,
    "elo_diff": 253,
    "elo1": 1988,
    "elo2": 1735,
    "h2h_record": "0-0",
    "h2h_surf": "0-0 on clay",
    "p1_streak": 0,
    "p2_streak": 5,
    "p1_fatigue": 0,
    "p2_fatigue": 1,
    "p1_fatigue.1": 0,
    "p2_fatigue.1": 1,
    "p1_serve_in": 60.7,
    "p2_serve_in": 64.1,
    "p1_serve_won": 74.8,
    "p2_serve_won": 69.5,
    "p1_second_won": 55.6,
    "p2_second_won": 50.3,
    "p1_bp_conv": 50.7,
    "p2_bp_conv": 54.5,
    "p1_win_rate": 65.2,
    "p2_win_rate": 54.7,
    "tour": "atp",
    "generated": "2026-06-02 07:06",
    "p1_flag": "hr",
    "p2_flag": "es",
    "market_flag": false
  },
  {
    "p1_id": 104494,
    "p2_id": 74151,
    "p1_name": "Diego Dedura",
    "p2_name": "Max Wiskandt",
    "surface": "clay",
    "tournament": "Bad Rappenau Challenger",
    "tournamentId": 21735,
    "match_date": "2026-06-02",
    "p1_win": 0.851,
    "p2_win": 0.149,
    "fair_p1": 1.18,
    "fair_p2": 6.71,
    "elo_diff": 267,
    "elo1": 1795,
    "elo2": 1528,
    "h2h_record": "0-0",
    "h2h_surf": "0-0 on clay",
    "p1_streak": 0,
    "p2_streak": 0,
    "p1_fatigue": 1,
    "p2_fatigue": 0,
    "p1_fatigue.1": 1,
    "p2_fatigue.1": 0,
    "p1_serve_in": 66.6,
    "p2_serve_in": 62.3,
    "p1_serve_won": 68,
    "p2_serve_won": 73.1,
    "p1_second_won": 56.7,
    "p2_second_won": 54.8,
    "p1_bp_conv": 53.9,
    "p2_bp_conv": 51.5,
    "p1_win_rate": 59.1,
    "p2_win_rate": 45.1,
    "tour": "atp",
    "generated": "2026-06-02 07:06",
    "p1_flag": "de",
    "p2_flag": "de",
    "market_flag": false
  },
  {
    "p1_id": 61857,
    "p2_id": 20104,
    "p1_name": "Valentin Royer",
    "p2_name": "Marco Cecchinato",
    "surface": "clay",
    "tournament": "Perugia Challenger",
    "tournamentId": 21734,
    "match_date": "2026-06-03",
    "p1_win": 0.771,
    "p2_win": 0.229,
    "fair_p1": 1.3,
    "fair_p2": 4.37,
    "elo_diff": 67,
    "elo1": 1842,
    "elo2": 1775,
    "h2h_record": "2-0",
    "h2h_surf": "2-0 on clay",
    "p1_streak": 0,
    "p2_streak": 0,
    "p1_fatigue": 1,
    "p2_fatigue": 1,
    "p1_fatigue.1": 1,
    "p2_fatigue.1": 1,
    "p1_serve_in": 63.6,
    "p2_serve_in": 64.8,
    "p1_serve_won": 74.4,
    "p2_serve_won": 73.3,
    "p1_second_won": 57.9,
    "p2_second_won": 58.5,
    "p1_bp_conv": 44.4,
    "p2_bp_conv": 46.5,
    "p1_win_rate": 64.9,
    "p2_win_rate": 56.6,
    "tour": "atp",
    "generated": "2026-06-02 07:06",
    "p1_flag": "fr",
    "p2_flag": "it",
    "market_flag": false
  },
  {
    "p1_id": 83555,
    "p2_id": 48011,
    "p1_name": "Robin Bertrand",
    "p2_name": "Patrick Zahraj",
    "surface": "hard",
    "tournament": "Centurion 2 Challenger",
    "tournamentId": 21738,
    "match_date": "2026-06-02",
    "p1_win": 0.769,
    "p2_win": 0.231,
    "fair_p1": 1.3,
    "fair_p2": 4.33,
    "elo_diff": 182,
    "elo1": 1752,
    "elo2": 1571,
    "h2h_record": "0-0",
    "h2h_surf": "0-0 on hard",
    "p1_streak": 0,
    "p2_streak": 0,
    "p1_fatigue": 0,
    "p2_fatigue": 0,
    "p1_fatigue.1": 0,
    "p2_fatigue.1": 0,
    "p1_serve_in": 64.9,
    "p2_serve_in": 62.2,
    "p1_serve_won": 71.5,
    "p2_serve_won": 72.7,
    "p1_second_won": 55.4,
    "p2_second_won": 52.9,
    "p1_bp_conv": 55.8,
    "p2_bp_conv": 48,
    "p1_win_rate": 54.6,
    "p2_win_rate": 49.8,
    "tour": "atp",
    "generated": "2026-06-02 07:06",
    "p1_flag": "fr",
    "p2_flag": "de",
    "market_flag": false
  },
  {
    "p1_id": 92094,
    "p2_id": 17123,
    "p1_name": "Henry Searle",
    "p2_name": "Mitchell Krueger",
    "surface": "hard",
    "tournament": "Tyler Challenger",
    "tournamentId": 21737,
    "match_date": "2026-06-02",
    "p1_win": 0.756,
    "p2_win": 0.244,
    "fair_p1": 1.32,
    "fair_p2": 4.1,
    "elo_diff": 286,
    "elo1": 1842,
    "elo2": 1556,
    "h2h_record": "0-0",
    "h2h_surf": "0-0 on hard",
    "p1_streak": 4,
    "p2_streak": 0,
    "p1_fatigue": 2,
    "p2_fatigue": 2,
    "p1_fatigue.1": 2,
    "p2_fatigue.1": 2,
    "p1_serve_in": 63.5,
    "p2_serve_in": 62.9,
    "p1_serve_won": 76.1,
    "p2_serve_won": 75.9,
    "p1_second_won": 57.3,
    "p2_second_won": 57.1,
    "p1_bp_conv": 46.7,
    "p2_bp_conv": 46.5,
    "p1_win_rate": 61.1,
    "p2_win_rate": 47.3,
    "tour": "atp",
    "generated": "2026-06-02 07:06",
    "p1_flag": "gb",
    "p2_flag": "us",
    "market_flag": false
  },
  {
    "p1_id": 26140,
    "p2_id": 55252,
    "p1_name": "Zhizhen Zhang",
    "p2_name": "Otto Virtanen",
    "surface": "grass",
    "tournament": "Birmingham Challenger",
    "tournamentId": 21733,
    "match_date": "2026-06-02",
    "p1_win": 0.248,
    "p2_win": 0.752,
    "fair_p1": 4.03,
    "fair_p2": 1.33,
    "elo_diff": -173,
    "elo1": 1531,
    "elo2": 1705,
    "h2h_record": "0-1",
    "h2h_surf": "0-0 on grass",
    "p1_streak": 0,
    "p2_streak": 0,
    "p1_fatigue": 2,
    "p2_fatigue": 0,
    "p1_fatigue.1": 2,
    "p2_fatigue.1": 0,
    "p1_serve_in": 64.7,
    "p2_serve_in": 62.3,
    "p1_serve_won": 79.4,
    "p2_serve_won": 78.6,
    "p1_second_won": 57.9,
    "p2_second_won": 56.1,
    "p1_bp_conv": 52.9,
    "p2_bp_conv": 46.2,
    "p1_win_rate": 44.2,
    "p2_win_rate": 69.2,
    "tour": "atp",
    "generated": "2026-06-02 07:06",
    "p1_flag": "cn",
    "p2_flag": "fi",
    "market_flag": false
  },
  {
    "p1_id": 34537,
    "p2_id": 59169,
    "p1_name": "Fajing Sun",
    "p2_name": "Andre Ilagan",
    "surface": "hard",
    "tournament": "Tyler Challenger",
    "tournamentId": 21737,
    "match_date": "2026-06-02",
    "p1_win": 0.75,
    "p2_win": 0.25,
    "fair_p1": 1.33,
    "fair_p2": 4,
    "elo_diff": 202,
    "elo1": 1770,
    "elo2": 1568,
    "h2h_record": "0-0",
    "h2h_surf": "0-0 on hard",
    "p1_streak": 5,
    "p2_streak": 1,
    "p1_fatigue": 0,
    "p2_fatigue": 1,
    "p1_fatigue.1": 0,
    "p2_fatigue.1": 1,
    "p1_serve_in": 59.4,
    "p2_serve_in": 63.8,
    "p1_serve_won": 76.7,
    "p2_serve_won": 74.8,
    "p1_second_won": 57.8,
    "p2_second_won": 52.5,
    "p1_bp_conv": 50.2,
    "p2_bp_conv": 49.2,
    "p1_win_rate": 57.4,
    "p2_win_rate": 54.4,
    "tour": "atp",
    "generated": "2026-06-02 07:06",
    "p1_flag": "cn",
    "p2_flag": "us",
    "market_flag": false
  },
  {
    "p1_id": 26218,
    "p2_id": 24721,
    "p1_name": "Elias Ymer",
    "p2_name": "Christopher O'Connell",
    "surface": "grass",
    "tournament": "Birmingham Challenger",
    "tournamentId": 21733,
    "match_date": "2026-06-02",
    "p1_win": 0.746,
    "p2_win": 0.254,
    "fair_p1": 1.34,
    "fair_p2": 3.94,
    "elo_diff": 169,
    "elo1": 1567,
    "elo2": 1398,
    "h2h_record": "1-0",
    "h2h_surf": "0-0 on grass",
    "p1_streak": 0,
    "p2_streak": 0,
    "p1_fatigue": 1,
    "p2_fatigue": 1,
    "p1_fatigue.1": 1,
    "p2_fatigue.1": 1,
    "p1_serve_in": 61.2,
    "p2_serve_in": 60.5,
    "p1_serve_won": 77,
    "p2_serve_won": 78.4,
    "p1_second_won": 53.6,
    "p2_second_won": 58.4,
    "p1_bp_conv": 48.6,
    "p2_bp_conv": 43.8,
    "p1_win_rate": 51.4,
    "p2_win_rate": 46.6,
    "tour": "atp",
    "generated": "2026-06-02 07:06",
    "p1_flag": "se",
    "p2_flag": "au",
    "market_flag": false
  },
  {
    "p1_id": 99691,
    "p2_id": 24008,
    "p1_name": "Rafael Jodar",
    "p2_name": "Alexander Zverev",
    "surface": "clay",
    "tournament": "French Open - Paris",
    "tournamentId": 21329,
    "match_date": "2026-06-02",
    "p1_win": 0.262,
    "p2_win": 0.738,
    "fair_p1": 3.82,
    "fair_p2": 1.36,
    "elo_diff": -22,
    "elo1": 1915,
    "elo2": 1937,
    "h2h_record": "0-0",
    "h2h_surf": "0-0 on clay",
    "p1_streak": 2,
    "p2_streak": 1,
    "p1_fatigue": 3,
    "p2_fatigue": 0,
    "p1_fatigue.1": 3,
    "p2_fatigue.1": 0,
    "p1_serve_in": 61.8,
    "p2_serve_in": 69,
    "p1_serve_won": 75.3,
    "p2_serve_won": 77.2,
    "p1_second_won": 58.7,
    "p2_second_won": 58,
    "p1_bp_conv": 51.7,
    "p2_bp_conv": 51.6,
    "p1_win_rate": 79.3,
    "p2_win_rate": 75,
    "tour": "atp",
    "generated": "2026-06-02 07:06",
    "p1_flag": "es",
    "p2_flag": "de",
    "p1_odds": 5.19,
    "p2_odds": 1.18,
    "bookmaker": "pinnacle",
    "market_implied_p1": 18.5,
    "market_deviation": 7.7,
    "market_flag": false
  },
  {
    "p1_id": 86691,
    "p2_id": 91521,
    "p1_name": "Jakub Mensik",
    "p2_name": "Joao Fonseca",
    "surface": "clay",
    "tournament": "French Open - Paris",
    "tournamentId": 21329,
    "match_date": "2026-06-02",
    "p1_win": 0.266,
    "p2_win": 0.734,
    "fair_p1": 3.76,
    "fair_p2": 1.36,
    "elo_diff": -187,
    "elo1": 1639,
    "elo2": 1825,
    "h2h_record": "0-1",
    "h2h_surf": "0-0 on clay",
    "p1_streak": 1,
    "p2_streak": 0,
    "p1_fatigue": 3,
    "p2_fatigue": 0,
    "p1_fatigue.1": 3,
    "p2_fatigue.1": 0,
    "p1_serve_in": 61.6,
    "p2_serve_in": 66,
    "p1_serve_won": 77.9,
    "p2_serve_won": 74.8,
    "p1_second_won": 55.1,
    "p2_second_won": 56.5,
    "p1_bp_conv": 49.7,
    "p2_bp_conv": 47.1,
    "p1_win_rate": 62.9,
    "p2_win_rate": 62.1,
    "tour": "atp",
    "generated": "2026-06-02 07:06",
    "p1_flag": "cz",
    "p2_flag": "br",
    "p1_odds": 2.75,
    "p2_odds": 1.51,
    "bookmaker": "pinnacle",
    "market_implied_p1": 35.4,
    "market_deviation": 8.8,
    "market_flag": false
  },
  {
    "p1_id": 27783,
    "p2_id": 71188,
    "p1_name": "Mukund Sasikumar",
    "p2_name": "Giles Hussey",
    "surface": "hard",
    "tournament": "Centurion 2 Challenger",
    "tournamentId": 21738,
    "match_date": "2026-06-02",
    "p1_win": 0.278,
    "p2_win": 0.722,
    "fair_p1": 3.6,
    "fair_p2": 1.39,
    "elo_diff": -166,
    "elo1": 1548,
    "elo2": 1714,
    "h2h_record": "0-0",
    "h2h_surf": "0-0 on hard",
    "p1_streak": 0,
    "p2_streak": 0,
    "p1_fatigue": 1,
    "p2_fatigue": 2,
    "p1_fatigue.1": 1,
    "p2_fatigue.1": 2,
    "p1_serve_in": 62.1,
    "p2_serve_in": 61.9,
    "p1_serve_won": 77.5,
    "p2_serve_won": 73,
    "p1_second_won": 55.7,
    "p2_second_won": 57.5,
    "p1_bp_conv": 49.2,
    "p2_bp_conv": 48.6,
    "p1_win_rate": 47.5,
    "p2_win_rate": 58.4,
    "tour": "atp",
    "generated": "2026-06-02 07:06",
    "p1_flag": "in",
    "p2_flag": "gb",
    "market_flag": false
  },
  {
    "p1_id": 52721,
    "p2_id": 56195,
    "p1_name": "Sebastian Baez",
    "p2_name": "Tristan Boyer",
    "surface": "clay",
    "tournament": "Prostejov Challenger",
    "tournamentId": 21736,
    "match_date": "2026-06-03",
    "p1_win": 0.721,
    "p2_win": 0.279,
    "fair_p1": 1.39,
    "fair_p2": 3.58,
    "elo_diff": 151,
    "elo1": 1718,
    "elo2": 1567,
    "h2h_record": "0-0",
    "h2h_surf": "0-0 on clay",
    "p1_streak": 0,
    "p2_streak": 0,
    "p1_fatigue": 3,
    "p2_fatigue": 1,
    "p1_fatigue.1": 3,
    "p2_fatigue.1": 1,
    "p1_serve_in": 66.9,
    "p2_serve_in": 61.5,
    "p1_serve_won": 70.1,
    "p2_serve_won": 73.4,
    "p1_second_won": 55.2,
    "p2_second_won": 53.2,
    "p1_bp_conv": 51.7,
    "p2_bp_conv": 48.9,
    "p1_win_rate": 54,
    "p2_win_rate": 47.3,
    "tour": "atp",
    "generated": "2026-06-02 07:06",
    "p1_flag": "ar",
    "p2_flag": "us",
    "market_flag": false
  },
  {
    "p1_id": 28685,
    "p2_id": 17928,
    "p1_name": "Viktor Durasovic",
    "p2_name": "Norbert Gombos",
    "surface": "clay",
    "tournament": "Prostejov Challenger",
    "tournamentId": 21736,
    "match_date": "2026-06-02",
    "p1_win": 0.284,
    "p2_win": 0.716,
    "fair_p1": 3.52,
    "fair_p2": 1.4,
    "elo_diff": -164,
    "elo1": 1536,
    "elo2": 1700,
    "h2h_record": "0-0",
    "h2h_surf": "0-0 on clay",
    "p1_streak": 0,
    "p2_streak": 0,
    "p1_fatigue": 1,
    "p2_fatigue": 0,
    "p1_fatigue.1": 1,
    "p2_fatigue.1": 0,
    "p1_serve_in": 60.8,
    "p2_serve_in": 60.1,
    "p1_serve_won": 73.9,
    "p2_serve_won": 74.9,
    "p1_second_won": 55.9,
    "p2_second_won": 54.6,
    "p1_bp_conv": 46.7,
    "p2_bp_conv": 50.6,
    "p1_win_rate": 42.5,
    "p2_win_rate": 54,
    "tour": "atp",
    "generated": "2026-06-02 07:06",
    "p1_flag": "no",
    "p2_flag": "sk",
    "market_flag": false
  },
  {
    "p1_id": 1837,
    "p2_id": 86156,
    "p1_name": "Roberto Bautista Agut",
    "p2_name": "Hynek Barton",
    "surface": "clay",
    "tournament": "Prostejov Challenger",
    "tournamentId": 21736,
    "match_date": "2026-06-02",
    "p1_win": 0.289,
    "p2_win": 0.711,
    "fair_p1": 3.46,
    "fair_p2": 1.41,
    "elo_diff": -156,
    "elo1": 1553,
    "elo2": 1709,
    "h2h_record": "0-0",
    "h2h_surf": "0-0 on clay",
    "p1_streak": 0,
    "p2_streak": 0,
    "p1_fatigue": 0,
    "p2_fatigue": 1,
    "p1_fatigue.1": 0,
    "p2_fatigue.1": 1,
    "p1_serve_in": 67,
    "p2_serve_in": 60.8,
    "p1_serve_won": 73.9,
    "p2_serve_won": 74.5,
    "p1_second_won": 57.5,
    "p2_second_won": 55.2,
    "p1_bp_conv": 54.4,
    "p2_bp_conv": 48.9,
    "p1_win_rate": 42,
    "p2_win_rate": 62.8,
    "tour": "atp",
    "generated": "2026-06-02 07:06",
    "p1_flag": "es",
    "p2_flag": "cz",
    "market_flag": false
  },
  {
    "p1_id": 40434,
    "p2_id": 67546,
    "p1_name": "Felix Auger Aliassime",
    "p2_name": "Flavio Cobolli",
    "surface": "clay",
    "tournament": "French Open - Paris",
    "tournamentId": 21329,
    "match_date": "2026-06-03",
    "p1_win": 0.294,
    "p2_win": 0.706,
    "fair_p1": 3.4,
    "fair_p2": 1.42,
    "elo_diff": -156,
    "elo1": 1717,
    "elo2": 1873,
    "h2h_record": "0-2",
    "h2h_surf": "0-0 on clay",
    "p1_streak": 1,
    "p2_streak": 1,
    "p1_fatigue": 4,
    "p2_fatigue": 0,
    "p1_fatigue.1": 4,
    "p2_fatigue.1": 0,
    "p1_serve_in": 65.1,
    "p2_serve_in": 59,
    "p1_serve_won": 79.3,
    "p2_serve_won": 75.3,
    "p1_second_won": 58.3,
    "p2_second_won": 57.6,
    "p1_bp_conv": 44.7,
    "p2_bp_conv": 46.5,
    "p1_win_rate": 65.1,
    "p2_win_rate": 63.9,
    "tour": "atp",
    "generated": "2026-06-02 07:06",
    "p1_flag": "ca",
    "p2_flag": "it",
    "p1_odds": 1.98,
    "p2_odds": 1.9,
    "bookmaker": "pinnacle",
    "market_implied_p1": 49,
    "market_deviation": 19.6,
    "market_flag": true
  },
  {
    "p1_id": 75024,
    "p2_id": 77192,
    "p1_name": "Blaise Bicknell",
    "p2_name": "Johannus Monday",
    "surface": "hard",
    "tournament": "Tyler Challenger",
    "tournamentId": 21737,
    "match_date": "2026-06-02",
    "p1_win": 0.706,
    "p2_win": 0.294,
    "fair_p1": 1.42,
    "fair_p2": 3.4,
    "elo_diff": 142,
    "elo1": 1734,
    "elo2": 1592,
    "h2h_record": "1-1",
    "h2h_surf": "1-1 on hard",
    "p1_streak": 0,
    "p2_streak": 0,
    "p1_fatigue": 0,
    "p2_fatigue": 2,
    "p1_fatigue.1": 0,
    "p2_fatigue.1": 2,
    "p1_serve_in": 67.5,
    "p2_serve_in": 66.7,
    "p1_serve_won": 74.4,
    "p2_serve_won": 77,
    "p1_second_won": 56.5,
    "p2_second_won": 59.2,
    "p1_bp_conv": 46.8,
    "p2_bp_conv": 52.5,
    "p1_win_rate": 57.3,
    "p2_win_rate": 60.1,
    "tour": "atp",
    "generated": "2026-06-02 07:06",
    "p1_flag": "",
    "p2_flag": "gb",
    "market_flag": false
  },
  {
    "p1_id": 48871,
    "p2_id": 56590,
    "p1_name": "Yuta Shimizu",
    "p2_name": "Dane Sweeny",
    "surface": "hard",
    "tournament": "Tyler Challenger",
    "tournamentId": 21737,
    "match_date": "2026-06-02",
    "p1_win": 0.322,
    "p2_win": 0.678,
    "fair_p1": 3.11,
    "fair_p2": 1.47,
    "elo_diff": -65,
    "elo1": 1688,
    "elo2": 1754,
    "h2h_record": "0-0",
    "h2h_surf": "0-0 on hard",
    "p1_streak": 1,
    "p2_streak": 0,
    "p1_fatigue": 0,
    "p2_fatigue": 1,
    "p1_fatigue.1": 0,
    "p2_fatigue.1": 1,
    "p1_serve_in": 63,
    "p2_serve_in": 63.2,
    "p1_serve_won": 73.5,
    "p2_serve_won": 72.6,
    "p1_second_won": 52.8,
    "p2_second_won": 57.5,
    "p1_bp_conv": 47.6,
    "p2_bp_conv": 49.4,
    "p1_win_rate": 55.3,
    "p2_win_rate": 61.7,
    "tour": "atp",
    "generated": "2026-06-02 07:06",
    "p1_flag": "jp",
    "p2_flag": "au",
    "market_flag": false
  },
  {
    "p1_id": 39863,
    "p2_id": 73742,
    "p1_name": "Sho Shimabukuro",
    "p2_name": "Shintaro Mochizuki",
    "surface": "grass",
    "tournament": "Birmingham Challenger",
    "tournamentId": 21733,
    "match_date": "2026-06-02",
    "p1_win": 0.334,
    "p2_win": 0.666,
    "fair_p1": 2.99,
    "fair_p2": 1.5,
    "elo_diff": -151,
    "elo1": 1522,
    "elo2": 1673,
    "h2h_record": "0-0",
    "h2h_surf": "0-0 on grass",
    "p1_streak": 0,
    "p2_streak": 0,
    "p1_fatigue": 1,
    "p2_fatigue": 5,
    "p1_fatigue.1": 1,
    "p2_fatigue.1": 5,
    "p1_serve_in": 59.4,
    "p2_serve_in": 58.4,
    "p1_serve_won": 76.1,
    "p2_serve_won": 74.2,
    "p1_second_won": 58.4,
    "p2_second_won": 53.3,
    "p1_bp_conv": 50.6,
    "p2_bp_conv": 53.9,
    "p1_win_rate": 59.7,
    "p2_win_rate": 50.2,
    "tour": "atp",
    "generated": "2026-06-02 07:06",
    "p1_flag": "jp",
    "p2_flag": "jp",
    "market_flag": false
  },
  {
    "p1_id": 95311,
    "p2_id": 60625,
    "p1_name": "Max Schoenhaus",
    "p2_name": "Alejandro Moro Canas",
    "surface": "clay",
    "tournament": "Bad Rappenau Challenger",
    "tournamentId": 21735,
    "match_date": "2026-06-03",
    "p1_win": 0.338,
    "p2_win": 0.662,
    "fair_p1": 2.96,
    "fair_p2": 1.51,
    "elo_diff": -88,
    "elo1": 1633,
    "elo2": 1722,
    "h2h_record": "0-0",
    "h2h_surf": "0-0 on clay",
    "p1_streak": 0,
    "p2_streak": 0,
    "p1_fatigue": 3,
    "p2_fatigue": 2,
    "p1_fatigue.1": 3,
    "p2_fatigue.1": 2,
    "p1_serve_in": 57.9,
    "p2_serve_in": 64.2,
    "p1_serve_won": 74.6,
    "p2_serve_won": 71.9,
    "p1_second_won": 53.2,
    "p2_second_won": 54,
    "p1_bp_conv": 53.5,
    "p2_bp_conv": 49.6,
    "p1_win_rate": 48.8,
    "p2_win_rate": 53.1,
    "tour": "atp",
    "generated": "2026-06-02 07:06",
    "p1_flag": "de",
    "p2_flag": "es",
    "market_flag": false
  },
  {
    "p1_id": 9503,
    "p2_id": 32631,
    "p1_name": "Ajla Tomljanovic",
    "p2_name": "Katie Swan",
    "surface": "grass",
    "tournament": "Lexus Birmingham Open - Birmingham",
    "tournamentId": 17034,
    "match_date": "2026-06-02",
    "p1_win": 0.661,
    "p2_win": 0.339,
    "fair_p1": 1.51,
    "fair_p2": 2.95,
    "elo_diff": 55,
    "elo1": 1555,
    "elo2": 1500,
    "h2h_record": "0-0",
    "h2h_surf": "0-0 on grass",
    "p1_fatigue": 0,
    "p2_fatigue": 2,
    "p1_serve_in": 64.8,
    "p2_serve_in": 65.9,
    "p1_serve_won": 68.9,
    "p2_serve_won": 72.8,
    "p1_second_won": 48.3,
    "p2_second_won": 50.6,
    "p1_bp_conv": 53,
    "p2_bp_conv": 52.7,
    "p1_win_rate": 55.8,
    "p2_win_rate": 62.1,
    "tour": "wta",
    "generated": "2026-06-02 07:06",
    "p1_flag": "",
    "p2_flag": "",
    "market_flag": false
  },
  {
    "p1_id": 84561,
    "p2_id": 56197,
    "p1_name": "Marko Topo",
    "p2_name": "Emilio Nava",
    "surface": "clay",
    "tournament": "Bad Rappenau Challenger",
    "tournamentId": 21735,
    "match_date": "2026-06-03",
    "p1_win": 0.361,
    "p2_win": 0.639,
    "fair_p1": 2.77,
    "fair_p2": 1.56,
    "elo_diff": -69,
    "elo1": 1658,
    "elo2": 1727,
    "h2h_record": "1-0",
    "h2h_surf": "1-0 on clay",
    "p1_streak": 0,
    "p2_streak": 2,
    "p1_fatigue": 0,
    "p2_fatigue": 0,
    "p1_fatigue.1": 0,
    "p2_fatigue.1": 0,
    "p1_serve_in": 62.2,
    "p2_serve_in": 63.1,
    "p1_serve_won": 73.8,
    "p2_serve_won": 77,
    "p1_second_won": 57.3,
    "p2_second_won": 55.4,
    "p1_bp_conv": 49.4,
    "p2_bp_conv": 49.6,
    "p1_win_rate": 57.7,
    "p2_win_rate": 60.6,
    "tour": "atp",
    "generated": "2026-06-02 07:06",
    "p1_flag": "rs",
    "p2_flag": "us",
    "market_flag": false
  },
  {
    "p1_id": 71129,
    "p2_id": 8757,
    "p1_name": "Georgia Pedone",
    "p2_name": "Ekaterine Gorgodze",
    "surface": "clay",
    "tournament": "Open delle Puglie - Foggia",
    "tournamentId": 17035,
    "match_date": "2026-06-02",
    "p1_win": 0.639,
    "p2_win": 0.361,
    "fair_p1": 1.56,
    "fair_p2": 2.77,
    "elo_diff": 116,
    "elo1": 1632,
    "elo2": 1517,
    "h2h_record": "0-0",
    "h2h_surf": "0-0 on clay",
    "p1_fatigue": 2,
    "p2_fatigue": 1,
    "p1_serve_in": 77,
    "p2_serve_in": 74,
    "p1_serve_won": 60.5,
    "p2_serve_won": 62.4,
    "p1_second_won": 51.6,
    "p2_second_won": 50.3,
    "p1_bp_conv": 57.6,
    "p2_bp_conv": 56.9,
    "p1_win_rate": 56.2,
    "p2_win_rate": 51.4,
    "tour": "wta",
    "generated": "2026-06-02 07:06",
    "p1_flag": "",
    "p2_flag": "",
    "market_flag": false
  },
  {
    "p1_id": 47752,
    "p2_id": 29953,
    "p1_name": "Adam Walton",
    "p2_name": "Tung-Lin Wu",
    "surface": "hard",
    "tournament": "Tyler Challenger",
    "tournamentId": 21737,
    "match_date": "2026-06-02",
    "p1_win": 0.633,
    "p2_win": 0.367,
    "fair_p1": 1.58,
    "fair_p2": 2.72,
    "elo_diff": 12,
    "elo1": 1764,
    "elo2": 1752,
    "h2h_record": "1-0",
    "h2h_surf": "1-0 on hard",
    "p1_streak": 0,
    "p2_streak": 1,
    "p1_fatigue": 1,
    "p2_fatigue": 0,
    "p1_fatigue.1": 1,
    "p2_fatigue.1": 0,
    "p1_serve_in": 62.5,
    "p2_serve_in": 65.3,
    "p1_serve_won": 78.3,
    "p2_serve_won": 75.5,
    "p1_second_won": 56.9,
    "p2_second_won": 56.2,
    "p1_bp_conv": 49.8,
    "p2_bp_conv": 49.7,
    "p1_win_rate": 54.8,
    "p2_win_rate": 59.9,
    "tour": "atp",
    "generated": "2026-06-02 07:06",
    "p1_flag": "au",
    "p2_flag": "tw",
    "market_flag": false
  },
  {
    "p1_id": 47557,
    "p2_id": 55257,
    "p1_name": "Chun Hsin Tseng",
    "p2_name": "Timofey Skatov",
    "surface": "clay",
    "tournament": "Perugia Challenger",
    "tournamentId": 21734,
    "match_date": "2026-06-03",
    "p1_win": 0.373,
    "p2_win": 0.627,
    "fair_p1": 2.68,
    "fair_p2": 1.59,
    "elo_diff": -51,
    "elo1": 1684,
    "elo2": 1735,
    "h2h_record": "0-0",
    "h2h_surf": "0-0 on clay",
    "p1_streak": 0,
    "p2_streak": 0,
    "p1_fatigue": 1,
    "p2_fatigue": 2,
    "p1_fatigue.1": 1,
    "p2_fatigue.1": 2,
    "p1_serve_in": 58.9,
    "p2_serve_in": 60.1,
    "p1_serve_won": 73.6,
    "p2_serve_won": 73.2,
    "p1_second_won": 57.2,
    "p2_second_won": 55.5,
    "p1_bp_conv": 53.5,
    "p2_bp_conv": 52.2,
    "p1_win_rate": 57.8,
    "p2_win_rate": 56.4,
    "tour": "atp",
    "generated": "2026-06-02 07:06",
    "p1_flag": "tw",
    "p2_flag": "kz",
    "market_flag": false
  },
  {
    "p1_id": 80500,
    "p2_id": 91428,
    "p1_name": "Milos Karol",
    "p2_name": "Carlo Alberto Caniato",
    "surface": "clay",
    "tournament": "Prostejov Challenger",
    "tournamentId": 21736,
    "match_date": "2026-06-02",
    "p1_win": 0.382,
    "p2_win": 0.618,
    "fair_p1": 2.62,
    "fair_p2": 1.62,
    "elo_diff": -140,
    "elo1": 1531,
    "elo2": 1671,
    "h2h_record": "1-0",
    "h2h_surf": "1-0 on clay",
    "p1_streak": 0,
    "p2_streak": 0,
    "p1_fatigue": 0,
    "p2_fatigue": 1,
    "p1_fatigue.1": 0,
    "p2_fatigue.1": 1,
    "p1_serve_in": 59.9,
    "p2_serve_in": 61.7,
    "p1_serve_won": 76.8,
    "p2_serve_won": 77.3,
    "p1_second_won": 55.3,
    "p2_second_won": 57.5,
    "p1_bp_conv": 50.8,
    "p2_bp_conv": 50.2,
    "p1_win_rate": 47.5,
    "p2_win_rate": 54,
    "tour": "atp",
    "generated": "2026-06-02 07:06",
    "p1_flag": "sk",
    "p2_flag": "it",
    "market_flag": false
  },
  {
    "p1_id": 79067,
    "p2_id": 28267,
    "p1_name": "Jack Pinnington Jones",
    "p2_name": "Aleksandar Vukic",
    "surface": "grass",
    "tournament": "Birmingham Challenger",
    "tournamentId": 21733,
    "match_date": "2026-06-02",
    "p1_win": 0.617,
    "p2_win": 0.383,
    "fair_p1": 1.62,
    "fair_p2": 2.61,
    "elo_diff": 85,
    "elo1": 1624,
    "elo2": 1539,
    "h2h_record": "0-0",
    "h2h_surf": "0-0 on grass",
    "p1_streak": 0,
    "p2_streak": 0,
    "p1_fatigue": 2,
    "p2_fatigue": 2,
    "p1_fatigue.1": 2,
    "p2_fatigue.1": 2,
    "p1_serve_in": 62.7,
    "p2_serve_in": 62.3,
    "p1_serve_won": 75.4,
    "p2_serve_won": 79.1,
    "p1_second_won": 53,
    "p2_second_won": 58.4,
    "p1_bp_conv": 51.8,
    "p2_bp_conv": 48.5,
    "p1_win_rate": 64.9,
    "p2_win_rate": 47.5,
    "tour": "atp",
    "generated": "2026-06-02 07:06",
    "p1_flag": "gb",
    "p2_flag": "au",
    "market_flag": false
  },
  {
    "p1_id": 64891,
    "p2_id": 41484,
    "p1_name": "Alexander Shevchenko",
    "p2_name": "Nikolas Sanchez-Izquierdo",
    "surface": "clay",
    "tournament": "Prostejov Challenger",
    "tournamentId": 21736,
    "match_date": "2026-06-03",
    "p1_win": 0.614,
    "p2_win": 0.386,
    "fair_p1": 1.63,
    "fair_p2": 2.59,
    "elo_diff": 5,
    "elo1": 1674,
    "elo2": 1669,
    "h2h_record": "0-0",
    "h2h_surf": "0-0 on clay",
    "p1_streak": 0,
    "p2_streak": 0,
    "p1_fatigue": 1,
    "p2_fatigue": 2,
    "p1_fatigue.1": 1,
    "p2_fatigue.1": 2,
    "p1_serve_in": 62.5,
    "p2_serve_in": 64.4,
    "p1_serve_won": 74.8,
    "p2_serve_won": 70.6,
    "p1_second_won": 53.8,
    "p2_second_won": 55.8,
    "p1_bp_conv": 51.1,
    "p2_bp_conv": 51.5,
    "p1_win_rate": 48.3,
    "p2_win_rate": 48.1,
    "tour": "atp",
    "generated": "2026-06-02 07:06",
    "p1_flag": "kz",
    "p2_flag": "es",
    "market_flag": false
  },
  {
    "p1_id": 52968,
    "p2_id": 56641,
    "p1_name": "Marvin Moeller",
    "p2_name": "Gauthier Onclin",
    "surface": "clay",
    "tournament": "Bad Rappenau Challenger",
    "tournamentId": 21735,
    "match_date": "2026-06-02",
    "p1_win": 0.387,
    "p2_win": 0.613,
    "fair_p1": 2.58,
    "fair_p2": 1.63,
    "elo_diff": -130,
    "elo1": 1608,
    "elo2": 1738,
    "h2h_record": "0-0",
    "h2h_surf": "0-0 on clay",
    "p1_streak": 0,
    "p2_streak": 9,
    "p1_fatigue": 1,
    "p2_fatigue": 2,
    "p1_fatigue.1": 1,
    "p2_fatigue.1": 2,
    "p1_serve_in": 64.9,
    "p2_serve_in": 61.5,
    "p1_serve_won": 70.4,
    "p2_serve_won": 71.3,
    "p1_second_won": 54,
    "p2_second_won": 52.5,
    "p1_bp_conv": 53.4,
    "p2_bp_conv": 52.8,
    "p1_win_rate": 56.3,
    "p2_win_rate": 57.1,
    "tour": "atp",
    "generated": "2026-06-02 07:06",
    "p1_flag": "de",
    "p2_flag": "be",
    "market_flag": false
  },
  {
    "p1_id": 29812,
    "p2_id": 73956,
    "p1_name": "Matteo Berrettini",
    "p2_name": "Matteo Arnaldi",
    "surface": "clay",
    "tournament": "French Open - Paris",
    "tournamentId": 21329,
    "match_date": "2026-06-03",
    "p1_win": 0.605,
    "p2_win": 0.395,
    "fair_p1": 1.65,
    "fair_p2": 2.53,
    "elo_diff": 142,
    "elo1": 1752,
    "elo2": 1610,
    "h2h_record": "0-0",
    "h2h_surf": "0-0 on clay",
    "p1_streak": 0,
    "p2_streak": 0,
    "p1_fatigue": 0,
    "p2_fatigue": 3,
    "p1_fatigue.1": 0,
    "p2_fatigue.1": 3,
    "p1_serve_in": 67.8,
    "p2_serve_in": 59.9,
    "p1_serve_won": 79.3,
    "p2_serve_won": 72.5,
    "p1_second_won": 60.5,
    "p2_second_won": 56.3,
    "p1_bp_conv": 44.3,
    "p2_bp_conv": 47.8,
    "p1_win_rate": 59.1,
    "p2_win_rate": 39.4,
    "tour": "atp",
    "generated": "2026-06-02 07:06",
    "p1_flag": "it",
    "p2_flag": "it",
    "p1_odds": 1.54,
    "p2_odds": 2.62,
    "bookmaker": "pinnacle",
    "market_implied_p1": 63,
    "market_deviation": 2.5,
    "market_flag": false
  },
  {
    "p1_id": 95464,
    "p2_id": 84236,
    "p1_name": "Matej Dodig",
    "p2_name": "Guy Den Ouden",
    "surface": "clay",
    "tournament": "Bad Rappenau Challenger",
    "tournamentId": 21735,
    "match_date": "2026-06-03",
    "p1_win": 0.601,
    "p2_win": 0.399,
    "fair_p1": 1.66,
    "fair_p2": 2.51,
    "elo_diff": 50,
    "elo1": 1770,
    "elo2": 1720,
    "h2h_record": "0-0",
    "h2h_surf": "0-0 on clay",
    "p1_streak": 0,
    "p2_streak": 0,
    "p1_fatigue": 1,
    "p2_fatigue": 2,
    "p1_fatigue.1": 1,
    "p2_fatigue.1": 2,
    "p1_serve_in": 61.8,
    "p2_serve_in": 61.7,
    "p1_serve_won": 73.2,
    "p2_serve_won": 71.6,
    "p1_second_won": 55.5,
    "p2_second_won": 52,
    "p1_bp_conv": 49,
    "p2_bp_conv": 53.7,
    "p1_win_rate": 57.6,
    "p2_win_rate": 59.3,
    "tour": "atp",
    "generated": "2026-06-02 07:06",
    "p1_flag": "hr",
    "p2_flag": "nl",
    "market_flag": false
  },
  {
    "p1_id": 26845,
    "p2_id": 74153,
    "p1_name": "Daniel Elahi Galan",
    "p2_name": "Max Hans Rehberg",
    "surface": "clay",
    "tournament": "Bad Rappenau Challenger",
    "tournamentId": 21735,
    "match_date": "2026-06-02",
    "p1_win": 0.598,
    "p2_win": 0.402,
    "fair_p1": 1.67,
    "fair_p2": 2.49,
    "elo_diff": 19,
    "elo1": 1556,
    "elo2": 1537,
    "h2h_record": "0-0",
    "h2h_surf": "0-0 on clay",
    "p1_streak": 0,
    "p2_streak": 0,
    "p1_fatigue": 1,
    "p2_fatigue": 0,
    "p1_fatigue.1": 1,
    "p2_fatigue.1": 0,
    "p1_serve_in": 62.3,
    "p2_serve_in": 67.4,
    "p1_serve_won": 73.3,
    "p2_serve_won": 72.4,
    "p1_second_won": 56.5,
    "p2_second_won": 55.6,
    "p1_bp_conv": 49.3,
    "p2_bp_conv": 53.4,
    "p1_win_rate": 46.6,
    "p2_win_rate": 54.6,
    "tour": "atp",
    "generated": "2026-06-02 07:06",
    "p1_flag": "co",
    "p2_flag": "de",
    "market_flag": false
  },
  {
    "p1_id": 79066,
    "p2_id": 33614,
    "p1_name": "Andres Martin",
    "p2_name": "Blake Ellis",
    "surface": "hard",
    "tournament": "Tyler Challenger",
    "tournamentId": 21737,
    "match_date": "2026-06-02",
    "p1_win": 0.414,
    "p2_win": 0.586,
    "fair_p1": 2.42,
    "fair_p2": 1.71,
    "elo_diff": -72,
    "elo1": 1600,
    "elo2": 1672,
    "h2h_record": "0-0",
    "h2h_surf": "0-0 on hard",
    "p1_streak": 0,
    "p2_streak": 2,
    "p1_fatigue": 3,
    "p2_fatigue": 0,
    "p1_fatigue.1": 3,
    "p2_fatigue.1": 0,
    "p1_serve_in": 63.4,
    "p2_serve_in": 60.7,
    "p1_serve_won": 73.6,
    "p2_serve_won": 77.4,
    "p1_second_won": 55.7,
    "p2_second_won": 56.1,
    "p1_bp_conv": 54.9,
    "p2_bp_conv": 44.2,
    "p1_win_rate": 51.2,
    "p2_win_rate": 57.7,
    "tour": "atp",
    "generated": "2026-06-02 07:06",
    "p1_flag": "us",
    "p2_flag": "au",
    "market_flag": false
  },
  {
    "p1_id": 97984,
    "p2_id": 63299,
    "p1_name": "Maxim Mrva",
    "p2_name": "Dalibor Svrcina",
    "surface": "clay",
    "tournament": "Prostejov Challenger",
    "tournamentId": 21736,
    "match_date": "2026-06-02",
    "p1_win": 0.419,
    "p2_win": 0.581,
    "fair_p1": 2.39,
    "fair_p2": 1.72,
    "elo_diff": -143,
    "elo1": 1599,
    "elo2": 1742,
    "h2h_record": "0-0",
    "h2h_surf": "0-0 on clay",
    "p1_streak": 0,
    "p2_streak": 4,
    "p1_fatigue": 0,
    "p2_fatigue": 0,
    "p1_fatigue.1": 0,
    "p2_fatigue.1": 0,
    "p1_serve_in": 59.9,
    "p2_serve_in": 65.9,
    "p1_serve_won": 67.8,
    "p2_serve_won": 68.4,
    "p1_second_won": 51.3,
    "p2_second_won": 52.1,
    "p1_bp_conv": 54.8,
    "p2_bp_conv": 56.4,
    "p1_win_rate": 49.2,
    "p2_win_rate": 62.3,
    "tour": "atp",
    "generated": "2026-06-02 07:06",
    "p1_flag": "cz",
    "p2_flag": "cz",
    "market_flag": false
  },
  {
    "p1_id": 64343,
    "p2_id": 48220,
    "p1_name": "Ashlyn Krueger",
    "p2_name": "Himeno Sakatsume",
    "surface": "grass",
    "tournament": "Lexus Birmingham Open - Birmingham",
    "tournamentId": 17034,
    "match_date": "2026-06-02",
    "p1_win": 0.579,
    "p2_win": 0.421,
    "fair_p1": 1.73,
    "fair_p2": 2.38,
    "elo_diff": -5,
    "elo1": 1494,
    "elo2": 1499,
    "h2h_record": "0-0",
    "h2h_surf": "0-0 on grass",
    "p1_fatigue": 0,
    "p2_fatigue": 1,
    "p1_serve_in": 64.7,
    "p2_serve_in": 66,
    "p1_serve_won": 69.7,
    "p2_serve_won": 66.6,
    "p1_second_won": 53.5,
    "p2_second_won": 53.9,
    "p1_bp_conv": 50.2,
    "p2_bp_conv": 56.4,
    "p1_win_rate": 45.5,
    "p2_win_rate": 62.2,
    "tour": "wta",
    "generated": "2026-06-02 07:06",
    "p1_flag": "",
    "p2_flag": "",
    "market_flag": false
  },
  {
    "p1_id": 71836,
    "p2_id": 75660,
    "p1_name": "Dominik Palan",
    "p2_name": "Alec Beckley",
    "surface": "hard",
    "tournament": "Centurion 2 Challenger",
    "tournamentId": 21738,
    "match_date": "2026-06-02",
    "p1_win": 0.422,
    "p2_win": 0.578,
    "fair_p1": 2.37,
    "fair_p2": 1.73,
    "elo_diff": -82,
    "elo1": 1551,
    "elo2": 1633,
    "h2h_record": "0-0",
    "h2h_surf": "0-0 on hard",
    "p1_streak": 0,
    "p2_streak": 0,
    "p1_fatigue": 1,
    "p2_fatigue": 1,
    "p1_fatigue.1": 1,
    "p2_fatigue.1": 1,
    "p1_serve_in": 63.9,
    "p2_serve_in": 62.9,
    "p1_serve_won": 78.6,
    "p2_serve_won": 73.3,
    "p1_second_won": 54.9,
    "p2_second_won": 55.7,
    "p1_bp_conv": 48.7,
    "p2_bp_conv": 50.5,
    "p1_win_rate": 50.1,
    "p2_win_rate": 53.7,
    "tour": "atp",
    "generated": "2026-06-02 07:06",
    "p1_flag": "cz",
    "p2_flag": "za",
    "market_flag": false
  },
  {
    "p1_id": 59411,
    "p2_id": 57375,
    "p1_name": "Darya Astakhova",
    "p2_name": "Lisa Pigato",
    "surface": "clay",
    "tournament": "Open delle Puglie - Foggia",
    "tournamentId": 17035,
    "match_date": "2026-06-03",
    "p1_win": 0.431,
    "p2_win": 0.569,
    "fair_p1": 2.32,
    "fair_p2": 1.76,
    "elo_diff": -103,
    "elo1": 1750,
    "elo2": 1854,
    "h2h_record": "0-0",
    "h2h_surf": "0-0 on clay",
    "p1_fatigue": 5,
    "p2_fatigue": 4,
    "p1_serve_in": 65.2,
    "p2_serve_in": 68.1,
    "p1_serve_won": 64.8,
    "p2_serve_won": 64.7,
    "p1_second_won": 47.9,
    "p2_second_won": 50.1,
    "p1_bp_conv": 59.1,
    "p2_bp_conv": 57.4,
    "p1_win_rate": 72.4,
    "p2_win_rate": 73.2,
    "tour": "wta",
    "generated": "2026-06-02 07:06",
    "p1_flag": "",
    "p2_flag": "",
    "market_flag": false
  },
  {
    "p1_id": 18094,
    "p2_id": 104215,
    "p1_name": "Mackenzie Mcdonald",
    "p2_name": "Nicolai Budkov Kjaer",
    "surface": "grass",
    "tournament": "Birmingham Challenger",
    "tournamentId": 21733,
    "match_date": "2026-06-02",
    "p1_win": 0.561,
    "p2_win": 0.439,
    "fair_p1": 1.78,
    "fair_p2": 2.28,
    "elo_diff": -11,
    "elo1": 1515,
    "elo2": 1526,
    "h2h_record": "1-0",
    "h2h_surf": "0-0 on grass",
    "p1_streak": 0,
    "p2_streak": 4,
    "p1_fatigue": 0,
    "p2_fatigue": 3,
    "p1_fatigue.1": 0,
    "p2_fatigue.1": 3,
    "p1_serve_in": 64,
    "p2_serve_in": 64,
    "p1_serve_won": 76.8,
    "p2_serve_won": 76.9,
    "p1_second_won": 58.1,
    "p2_second_won": 55.7,
    "p1_bp_conv": 52.1,
    "p2_bp_conv": 50,
    "p1_win_rate": 55.4,
    "p2_win_rate": 61.1,
    "tour": "atp",
    "generated": "2026-06-02 07:06",
    "p1_flag": "us",
    "p2_flag": "no",
    "market_flag": false
  },
  {
    "p1_id": 73983,
    "p2_id": 12190,
    "p1_name": "Gonzalo Bueno",
    "p2_name": "Dusan Lajovic",
    "surface": "clay",
    "tournament": "Perugia Challenger",
    "tournamentId": 21734,
    "match_date": "2026-06-02",
    "p1_win": 0.56,
    "p2_win": 0.44,
    "fair_p1": 1.79,
    "fair_p2": 2.27,
    "elo_diff": 39,
    "elo1": 1760,
    "elo2": 1721,
    "h2h_record": "0-0",
    "h2h_surf": "0-0 on clay",
    "p1_streak": 0,
    "p2_streak": 0,
    "p1_fatigue": 0,
    "p2_fatigue": 3,
    "p1_fatigue.1": 0,
    "p2_fatigue.1": 3,
    "p1_serve_in": 62.8,
    "p2_serve_in": 67.1,
    "p1_serve_won": 68.4,
    "p2_serve_won": 73.5,
    "p1_second_won": 53.3,
    "p2_second_won": 56.6,
    "p1_bp_conv": 54.4,
    "p2_bp_conv": 51.1,
    "p1_win_rate": 58.2,
    "p2_win_rate": 54.8,
    "tour": "atp",
    "generated": "2026-06-02 07:06",
    "p1_flag": "pe",
    "p2_flag": "rs",
    "market_flag": false
  },
  {
    "p1_id": 55828,
    "p2_id": 90774,
    "p1_name": "Clement Chidekh",
    "p2_name": "Filippo Romano",
    "surface": "grass",
    "tournament": "Birmingham Challenger",
    "tournamentId": 21733,
    "match_date": "2026-06-02",
    "p1_win": 0.56,
    "p2_win": 0.44,
    "fair_p1": 1.79,
    "fair_p2": 2.27,
    "elo_diff": -15,
    "elo1": 1485,
    "elo2": 1500,
    "h2h_record": "0-0",
    "h2h_surf": "0-0 on grass",
    "p1_streak": 0,
    "p2_streak": 0,
    "p1_fatigue": 2,
    "p2_fatigue": 2,
    "p1_fatigue.1": 2,
    "p2_fatigue.1": 2,
    "p1_serve_in": 62.8,
    "p2_serve_in": 64.7,
    "p1_serve_won": 72.6,
    "p2_serve_won": 76.6,
    "p1_second_won": 53.9,
    "p2_second_won": 53.5,
    "p1_bp_conv": 48.2,
    "p2_bp_conv": 47.8,
    "p1_win_rate": 63.2,
    "p2_win_rate": 62.6,
    "tour": "atp",
    "generated": "2026-06-02 07:06",
    "p1_flag": "fr",
    "p2_flag": "it",
    "market_flag": false
  },
  {
    "p1_id": 32365,
    "p2_id": 59575,
    "p1_name": "Miriam Bianca Bulgaru",
    "p2_name": "Noma Akugue Noha",
    "surface": "clay",
    "tournament": "Makarska Open - Makarska",
    "tournamentId": 17036,
    "match_date": "2026-06-02",
    "p1_win": 0.55,
    "p2_win": 0.45,
    "fair_p1": 1.82,
    "fair_p2": 2.22,
    "elo_diff": 12,
    "elo1": 1612,
    "elo2": 1600,
    "h2h_record": "1-0",
    "h2h_surf": "1-0 on clay",
    "p1_fatigue": 0,
    "p2_fatigue": 4,
    "p1_serve_in": 62.5,
    "p2_serve_in": 64.4,
    "p1_serve_won": 65.2,
    "p2_serve_won": 67,
    "p1_second_won": 50.3,
    "p2_second_won": 50.8,
    "p1_bp_conv": 55.4,
    "p2_bp_conv": 55.4,
    "p1_win_rate": 51.9,
    "p2_win_rate": 56.2,
    "tour": "wta",
    "generated": "2026-06-02 07:06",
    "p1_flag": "",
    "p2_flag": "",
    "market_flag": false
  },
  {
    "p1_id": 37577,
    "p2_id": 70459,
    "p1_name": "Genaro Alberto Olivieri",
    "p2_name": "Martin Krumich",
    "surface": "clay",
    "tournament": "Prostejov Challenger",
    "tournamentId": 21736,
    "match_date": "2026-06-02",
    "p1_win": 0.453,
    "p2_win": 0.547,
    "fair_p1": 2.21,
    "fair_p2": 1.83,
    "elo_diff": -47,
    "elo1": 1691,
    "elo2": 1738,
    "h2h_record": "0-0",
    "h2h_surf": "0-0 on clay",
    "p1_streak": 0,
    "p2_streak": 0,
    "p1_fatigue": 0,
    "p2_fatigue": 1,
    "p1_fatigue.1": 0,
    "p2_fatigue.1": 1,
    "p1_serve_in": 70.6,
    "p2_serve_in": 62.3,
    "p1_serve_won": 67.9,
    "p2_serve_won": 72.8,
    "p1_second_won": 55.3,
    "p2_second_won": 52.3,
    "p1_bp_conv": 53,
    "p2_bp_conv": 50.2,
    "p1_win_rate": 50.6,
    "p2_win_rate": 54.8,
    "tour": "atp",
    "generated": "2026-06-02 07:06",
    "p1_flag": "ar",
    "p2_flag": "cz",
    "market_flag": false
  },
  {
    "p1_id": 68090,
    "p2_id": 58149,
    "p1_name": "Jacob Fearnley",
    "p2_name": "Rinky Hijikata",
    "surface": "grass",
    "tournament": "Birmingham Challenger",
    "tournamentId": 21733,
    "match_date": "2026-06-02",
    "p1_win": 0.534,
    "p2_win": 0.466,
    "fair_p1": 1.87,
    "fair_p2": 2.15,
    "elo_diff": 45,
    "elo1": 1588,
    "elo2": 1543,
    "h2h_record": "0-0",
    "h2h_surf": "0-0 on grass",
    "p1_streak": 0,
    "p2_streak": 0,
    "p1_fatigue": 2,
    "p2_fatigue": 0,
    "p1_fatigue.1": 2,
    "p2_fatigue.1": 0,
    "p1_serve_in": 63.2,
    "p2_serve_in": 61.6,
    "p1_serve_won": 76.5,
    "p2_serve_won": 74.1,
    "p1_second_won": 55.5,
    "p2_second_won": 56.2,
    "p1_bp_conv": 49.5,
    "p2_bp_conv": 48.9,
    "p1_win_rate": 57.2,
    "p2_win_rate": 58,
    "tour": "atp",
    "generated": "2026-06-02 07:06",
    "p1_flag": "gb",
    "p2_flag": "au",
    "market_flag": false
  },
  {
    "p1_id": 83315,
    "p2_id": 28898,
    "p1_name": "James McCabe",
    "p2_name": "Kamil Majchrzak",
    "surface": "grass",
    "tournament": "Birmingham Challenger",
    "tournamentId": 21733,
    "match_date": "2026-06-02",
    "p1_win": 0.531,
    "p2_win": 0.469,
    "fair_p1": 1.88,
    "fair_p2": 2.13,
    "elo_diff": 98,
    "elo1": 1638,
    "elo2": 1541,
    "h2h_record": "0-0",
    "h2h_surf": "0-0 on grass",
    "p1_streak": 0,
    "p2_streak": 0,
    "p1_fatigue": 1,
    "p2_fatigue": 0,
    "p1_fatigue.1": 1,
    "p2_fatigue.1": 0,
    "p1_serve_in": 62.1,
    "p2_serve_in": 63.4,
    "p1_serve_won": 78,
    "p2_serve_won": 76.4,
    "p1_second_won": 57.2,
    "p2_second_won": 56.7,
    "p1_bp_conv": 47.6,
    "p2_bp_conv": 43.8,
    "p1_win_rate": 56.1,
    "p2_win_rate": 55.9,
    "tour": "atp",
    "generated": "2026-06-02 07:06",
    "p1_flag": "au",
    "p2_flag": "pl",
    "market_flag": false
  },
  {
    "p1_id": 44595,
    "p2_id": 73608,
    "p1_name": "Ugo Blanchet",
    "p2_name": "Felix Gill",
    "surface": "grass",
    "tournament": "Birmingham Challenger",
    "tournamentId": 21733,
    "match_date": "2026-06-02",
    "p1_win": 0.53,
    "p2_win": 0.47,
    "fair_p1": 1.89,
    "fair_p2": 2.13,
    "elo_diff": 36,
    "elo1": 1490,
    "elo2": 1454,
    "h2h_record": "0-0",
    "h2h_surf": "0-0 on grass",
    "p1_streak": 0,
    "p2_streak": 0,
    "p1_fatigue": 1,
    "p2_fatigue": 1,
    "p1_fatigue.1": 1,
    "p2_fatigue.1": 1,
    "p1_serve_in": 59.4,
    "p2_serve_in": 65.4,
    "p1_serve_won": 78.1,
    "p2_serve_won": 73.2,
    "p1_second_won": 59.5,
    "p2_second_won": 58.5,
    "p1_bp_conv": 47.5,
    "p2_bp_conv": 45.5,
    "p1_win_rate": 48.7,
    "p2_win_rate": 65.7,
    "tour": "atp",
    "generated": "2026-06-02 07:06",
    "p1_flag": "fr",
    "p2_flag": "gb",
    "market_flag": false
  },
  {
    "p1_id": 6201,
    "p2_id": 44197,
    "p1_name": "Madison Brengle",
    "p2_name": "Haley Giavara",
    "surface": "hard",
    "tournament": "W100 Sumter",
    "tournamentId": 17041,
    "match_date": "2026-06-02",
    "p1_win": 0.484,
    "p2_win": 0.516,
    "fair_p1": 2.07,
    "fair_p2": 1.94,
    "elo_diff": -33,
    "elo1": 1563,
    "elo2": 1596,
    "h2h_record": "0-0",
    "h2h_surf": "0-0 on hard",
    "p1_fatigue": 3,
    "p2_fatigue": 1,
    "p1_serve_in": 70.4,
    "p2_serve_in": 65.6,
    "p1_serve_won": 65.7,
    "p2_serve_won": 67.4,
    "p1_second_won": 49.3,
    "p2_second_won": 51.6,
    "p1_bp_conv": 58.6,
    "p2_bp_conv": 54.6,
    "p1_win_rate": 53,
    "p2_win_rate": 53.7,
    "tour": "wta",
    "generated": "2026-06-02 07:06",
    "p1_flag": "",
    "p2_flag": "",
    "market_flag": false
  },
  {
    "p1_id": 72174,
    "p2_id": 25513,
    "p1_name": "Celine Naef",
    "p2_name": "Maddison Inglis",
    "surface": "grass",
    "tournament": "Lexus Birmingham Open - Birmingham",
    "tournamentId": 17034,
    "match_date": "2026-06-02",
    "p1_win": 0.515,
    "p2_win": 0.485,
    "fair_p1": 1.94,
    "fair_p2": 2.06,
    "elo_diff": -2,
    "elo1": 1574,
    "elo2": 1576,
    "h2h_record": "0-0",
    "h2h_surf": "0-0 on grass",
    "p1_fatigue": 0,
    "p2_fatigue": 0,
    "p1_serve_in": 62.4,
    "p2_serve_in": 62.7,
    "p1_serve_won": 71.4,
    "p2_serve_won": 71.6,
    "p1_second_won": 51.5,
    "p2_second_won": 53.3,
    "p1_bp_conv": 53,
    "p2_bp_conv": 58.2,
    "p1_win_rate": 67.8,
    "p2_win_rate": 56.6,
    "tour": "wta",
    "generated": "2026-06-02 07:06",
    "p1_flag": "",
    "p2_flag": "",
    "market_flag": false
  },
  {
    "p1_id": 29457,
    "p2_id": 84060,
    "p1_name": "Andrea Pellegrino",
    "p2_name": "Maks Kasnikowski",
    "surface": "clay",
    "tournament": "Perugia Challenger",
    "tournamentId": 21734,
    "match_date": "2026-06-02",
    "p1_win": 0.489,
    "p2_win": 0.511,
    "fair_p1": 2.04,
    "fair_p2": 1.96,
    "elo_diff": -27,
    "elo1": 1707,
    "elo2": 1734,
    "h2h_record": "0-0",
    "h2h_surf": "0-0 on clay",
    "p1_streak": 0,
    "p2_streak": 0,
    "p1_fatigue": 0,
    "p2_fatigue": 2,
    "p1_fatigue.1": 0,
    "p2_fatigue.1": 2,
    "p1_serve_in": 62.8,
    "p2_serve_in": 60,
    "p1_serve_won": 73.2,
    "p2_serve_won": 74,
    "p1_second_won": 56.7,
    "p2_second_won": 55.1,
    "p1_bp_conv": 50.7,
    "p2_bp_conv": 50.3,
    "p1_win_rate": 56.8,
    "p2_win_rate": 56.8,
    "tour": "atp",
    "generated": "2026-06-02 07:06",
    "p1_flag": "it",
    "p2_flag": "pl",
    "market_flag": false
  },
  {
    "p1_id": 34539,
    "p2_id": 47021,
    "p1_name": "Alex Molcan",
    "p2_name": "Zsombor Piros",
    "surface": "clay",
    "tournament": "Prostejov Challenger",
    "tournamentId": 21736,
    "match_date": "2026-06-02",
    "p1_win": 0.511,
    "p2_win": 0.489,
    "fair_p1": 1.96,
    "fair_p2": 2.04,
    "elo_diff": 54,
    "elo1": 1929,
    "elo2": 1875,
    "h2h_record": "1-1",
    "h2h_surf": "1-1 on clay",
    "p1_streak": 0,
    "p2_streak": 0,
    "p1_fatigue": 4,
    "p2_fatigue": 2,
    "p1_fatigue.1": 4,
    "p2_fatigue.1": 2,
    "p1_serve_in": 61,
    "p2_serve_in": 59.8,
    "p1_serve_won": 73.1,
    "p2_serve_won": 72.6,
    "p1_second_won": 55.8,
    "p2_second_won": 57,
    "p1_bp_conv": 51.4,
    "p2_bp_conv": 48.2,
    "p1_win_rate": 68.9,
    "p2_win_rate": 64.2,
    "tour": "atp",
    "generated": "2026-06-02 07:06",
    "p1_flag": "sk",
    "p2_flag": "hu",
    "market_flag": false
  },
  {
    "p1_id": 71221,
    "p2_id": 18771,
    "p1_name": "Luca Nardi",
    "p2_name": "Oriol Roca Batalla",
    "surface": "clay",
    "tournament": "Perugia Challenger",
    "tournamentId": 21734,
    "match_date": "2026-06-02",
    "p1_win": 0.506,
    "p2_win": 0.494,
    "fair_p1": 1.98,
    "fair_p2": 2.02,
    "elo_diff": -72,
    "elo1": 1606,
    "elo2": 1678,
    "h2h_record": "0-0",
    "h2h_surf": "0-0 on clay",
    "p1_streak": 0,
    "p2_streak": 3,
    "p1_fatigue": 1,
    "p2_fatigue": 0,
    "p1_fatigue.1": 1,
    "p2_fatigue.1": 0,
    "p1_serve_in": 61.9,
    "p2_serve_in": 62.6,
    "p1_serve_won": 74.4,
    "p2_serve_won": 73.4,
    "p1_second_won": 56.9,
    "p2_second_won": 58.6,
    "p1_bp_conv": 51.8,
    "p2_bp_conv": 47.3,
    "p1_win_rate": 50.3,
    "p2_win_rate": 57.4,
    "tour": "atp",
    "generated": "2026-06-02 07:06",
    "p1_flag": "it",
    "p2_flag": "es",
    "market_flag": false
  },
  {
    "p1_id": 21506,
    "p2_id": 100196,
    "p1_name": "Roberto Carballes Baena",
    "p2_name": "Lorenzo Carboni",
    "surface": "clay",
    "tournament": "Perugia Challenger",
    "tournamentId": 21734,
    "match_date": "2026-06-02",
    "p1_win": 0.496,
    "p2_win": 0.504,
    "fair_p1": 2.02,
    "fair_p2": 1.98,
    "elo_diff": -43,
    "elo1": 1668,
    "elo2": 1711,
    "h2h_record": "0-0",
    "h2h_surf": "0-0 on clay",
    "p1_streak": 0,
    "p2_streak": 0,
    "p1_fatigue": 1,
    "p2_fatigue": 1,
    "p1_fatigue.1": 1,
    "p2_fatigue.1": 1,
    "p1_serve_in": 68,
    "p2_serve_in": 62.6,
    "p1_serve_won": 71.6,
    "p2_serve_won": 70.8,
    "p1_second_won": 54,
    "p2_second_won": 54.2,
    "p1_bp_conv": 50,
    "p2_bp_conv": 55.6,
    "p1_win_rate": 52.1,
    "p2_win_rate": 49.3,
    "tour": "atp",
    "generated": "2026-06-02 07:06",
    "p1_flag": "es",
    "p2_flag": "it",
    "market_flag": false
  }
]
